[
  {
    "type": "record",
    "name": "GraphicsPipelineShaderStage",
    "fields": [
      {
        "name": "entry_name",
        "type": "string"
      },
      {
        "name": "shader_module",
        "type": { "name": "asset_ref", "inner_type": "ShaderPackageAsset" }
      }
    ]
  },
  {
    "type": "record",
    "name": "MaterialPass",
    "fields": [
      {
        "name": "name",
        "type": "string"
      },
      {
        "name": "phase",
        "type": "string"
      },
      {
        "name": "fixed_function_state",
        "type": "string"
      },
      {
        "name": "vertex_stage",
        "type": "GraphicsPipelineShaderStage"
      },
      {
        "name": "fragment_stage",
        "type": "GraphicsPipelineShaderStage"
      }
    ]
  },
  {
    "type": "record",
    "name": "MaterialAsset",
    "default_thumbnail": "default_thumbnails/material.png",
    "fields": [
      {
        "name": "passes",
        "type": { "name": "dynamic_array", "inner_type": "MaterialPass" }
      }
    ]
  },
  {
    "type": "record",
    "name": "MaterialInstanceSlotAssignment",
    "fields": [
      {
        "name": "slot_name",
        "type": "string"
      },
      {
        "name": "array_index",
        "type": "u32"
      },
      {
        "name": "image",
        "type": { "name": "asset_ref", "inner_type": "GpuImageAsset" }
      },
      {
        "name": "sampler",
        "type": "string"
      },
      {
        "name": "buffer_data",
        "type": { "name": "nullable", "inner_type": "bytes" }
      }
    ]
  },
  {
    "type": "record",
    "name": "MaterialInstanceAsset",
    "fields": [
      {
        "name": "slot_assignments",
        "type": { "name": "dynamic_array", "inner_type": "MaterialInstanceSlotAssignment" }
      },
      {
        "name": "material",
        "type": { "name": "asset_ref", "inner_type": "MaterialAsset" }
      }
    ]
  }
]